<?xml version="1.0" encoding="utf-8" ?>
<elements>

	<element name="Unearthed Arcana: Magic Items of Eberron" type="Source" source="Core" id="ID_WOTC_SOURCE_UNEARTHED_ARCANA_20181008">
		<description>
			<p>This month's Unearthed Arcana looks at the magic items that are part of everyday life in the world of Eberron. Arcane focuses, enchanted clothing, warforged components, and more are all common sights for the citizens of the Five Nations.</p>
		</description>
		<setters>
			<set name="abbreviation">UA20181008</set>
			<set name="url">http://dnd.wizards.com/articles/unearthed-arcana/magic-items-eberron</set>
			<set name="author" abbreviation="WOTC" url="http://dnd.wizards.com">Wizards of the Coast</set>
			<set name="official">true</set>
			<set name="playtest">true</set>
			<set name="release">20181008</set>
		</setters>
	</element>

    <!-- placeholder -->

</elements>